buildpy.py
buildpy_bundler-0.1.2.dist-info/METADATA
buildpy_bundler-0.1.2.dist-info/WHEEL
buildpy_bundler-0.1.2.dist-info/entry_points.txt
buildpy_bundler-0.1.2.dist-info/licenses/LICENSE
buildpy_bundler-0.1.2.dist-info/RECORD
