Metadata-Version: 2.4
Name: buildpy-bundler
Version: 0.1.2
Summary: Build a minimal, bespoke CPython runtime from source with size reduction, static linking, and a zipped standard library.
Project-URL: Homepage, https://github.com/shakfu/buildpy
Project-URL: Repository, https://github.com/shakfu/buildpy
Project-URL: Issues, https://github.com/shakfu/buildpy/issues
Project-URL: Changelog, https://github.com/shakfu/buildpy/blob/main/py/buildpy/CHANGELOG.md
Author-email: Shakeeb Alireza <shakfu@users.noreply.github.com>
License-Expression: MIT
License-File: LICENSE
Keywords: build,compile,embedded,minimal,python,source,static
Classifier: Development Status :: 4 - Beta
Classifier: Environment :: Console
Classifier: Intended Audience :: Developers
Classifier: Operating System :: MacOS
Classifier: Operating System :: Microsoft :: Windows
Classifier: Operating System :: POSIX :: Linux
Classifier: Programming Language :: Python :: 3
Classifier: Programming Language :: Python :: 3.11
Classifier: Programming Language :: Python :: 3.12
Classifier: Programming Language :: Python :: 3.13
Classifier: Programming Language :: Python :: 3.14
Classifier: Topic :: Software Development :: Build Tools
Classifier: Topic :: Software Development :: Compilers
Classifier: Topic :: System :: Installation/Setup
Requires-Python: >=3.11
